[
    {
        "ID": "PL-1",
        "Titulo": "Intensamente 2",
        "Direccion": "Kelsey Mann",
        "Producción": "Mark Nielsen",
        "Valoracion": 4.6,
        "Genero": [
            "Animación", "Infantil", "Comedia", "Drama", "Aventura"
        ],
        "Fecha de estreno": "2025-06-15",
        "Categoria": "Animación"
    },
    {
        "ID": "PL-2",
        "Titulo": "Coco",
        "Direccion": "Lee Unkrich",
        "Producción": "Darla K. Anderson",
        "Valoracion": 4.8,
        "Genero": [
            "Animación", "Familia", "Musical", "Aventura"
        ],
        "Fecha de estreno": "2017-11-22",
        "Categoria": "Animación"
    },
    {
        "ID": "PL-3",
        "Titulo": "Frozen II",
        "Direccion": "Chris Buck",
        "Producción": "Peter Del Vecho",
        "Valoracion": 4.4,
        "Genero": [
            "Animación", "Fantasía", "Aventura", "Musical"
        ],
        "Fecha de estreno": "2019-11-22",
        "Categoria": "Animación"
    },
    {
        "ID": "PL-4",
        "Titulo": "Spider-Man: Into the Spider-Verse",
        "Direccion": "Bob Persichetti",
        "Producción": "Avi Arad",
        "Valoracion": 4.7,
        "Genero": [
            "Animación", "Acción", "Aventura", "Cómic"
        ],
        "Fecha de estreno": "2018-12-14",
        "Categoria": "Acción"
    },
    {
        "ID": "PL-5",
        "Titulo": "Toy Story 4",
        "Direccion": "Josh Cooley",
        "Producción": "Jonas Rivera",
        "Valoracion": 4.5,
        "Genero": [
            "Animación", "Aventura", "Comedia", "Familiar"
        ],
        "Fecha de estreno": "2019-06-21",
        "Categoria": "Animación"
    }
]

